{
  "users": [
    {
      "email": "emanuel1999emy@gmail.com",
      "password": "$2a$10$Tfrb77x5hnOfkkL6B3CBZeE/nbSOEhdEBV/5/XmaJyMlUozv4yznS",
      "firstname": "Tanemil",
      "lastname": "fdsfsd",
      "id": 1
    },
    {
      "email": "abc@gmail.com",
      "password": "$2a$10$0dNUb2hBEzf1NvcXvQUviOWUD4qhITo58f79zQJb9Jd6zU7APjB2O",
      "firstname": "Gianluca",
      "lastname": "Gallone",
      "id": 2
    },
    {
      "email": "cloud.gianluca@gmail.com",
      "password": "$2a$10$m1sCpJaPur.Khgjbpn6xLOiLQ52H5.1X2hRrE4lQe9D3ssCLt7wfa",
      "firstname": "Gianluca",
      "lastname": "Gallone",
      "id": 3
    }
  ],
  "clients": [
    {
      "ragioneSociale": "Eum nisi necessitati",
      "partitaIva": 53,
      "tipoCliente": "Quisquam deserunt ma",
      "email": "wysilu@mailinator.com",
      "pec": "Sunt aliquid cumque",
      "telefono": 67,
      "nomeContatto": "Voluptas aut sint et",
      "cognomeContatto": "Alias eos expedita ",
      "telefonoContatto": 27,
      "emailContatto": "girobyxa@mailinator.com",
      "indirizzoSedeOperativa.via": "Laboriosam illo eu ",
      "indirizzoSedeOperativa.civico": 28,
      "indirizzoSedeOperativa.cap": 83,
      "indirizzoSedeOperativa.localita": "Voluptatibus dolores",
      "indirizzoSedeOperativa.comune.id": 61,
      "indirizzoSedeOperativa.comune.nome": "Elit hic blanditiis",
      "indirizzoSedeOperativa.comune.provincia.id": 76,
      "indirizzoSedeOperativa.comune.provincia.nome": "Et ducimus alias od",
      "indirizzoSedeOperativa.comune.provincia.sigla": "Sed excepturi unde d",
      "indirizzoSedeLegale.via": "Dolor minim aute id",
      "indirizzoSedeLegale.civico": 96,
      "indirizzoSedeLegale.cap": 10,
      "indirizzoSedeLegale.localita": "Exercitationem id no",
      "indirizzoSedeLegale.comune.id": 54,
      "indirizzoSedeLegale.comune.nome": "Blanditiis non conse",
      "indirizzoSedeLegale.comune.provincia.id": 73,
      "indirizzoSedeLegale.comune.provincia.nome": "Laudantium quia ips",
      "indirizzoSedeLegale.comune.provincia.sigla": "Dolor sequi quae quo",
      "dataInserimento": 68,
      "dataUltimoContatto": 93,
      "id": 1
    },
    {
      "ragioneSociale": "Odit earum eligendi ",
      "partitaIva": 72,
      "tipoCliente": "Ipsa culpa natus so",
      "email": "vuno@mailinator.com",
      "pec": "Aliquip qui sit fug",
      "telefono": 43,
      "nomeContatto": "Pariatur Unde cum r",
      "cognomeContatto": "Dolore pariatur Exc",
      "telefonoContatto": 32,
      "emailContatto": "titynexi@mailinator.com",
      "indirizzoSedeOperativa.via": "Impedit voluptas do",
      "indirizzoSedeOperativa.civico": 58,
      "indirizzoSedeOperativa.cap": 90,
      "indirizzoSedeOperativa.localita": "Dicta qui excepteur ",
      "indirizzoSedeOperativa.comune.id": 61,
      "indirizzoSedeOperativa.comune.nome": "Accusantium nostrud ",
      "indirizzoSedeOperativa.comune.provincia.id": 62,
      "indirizzoSedeOperativa.comune.provincia.nome": "Duis illum in labor",
      "indirizzoSedeOperativa.comune.provincia.sigla": "Voluptatem itaque m",
      "indirizzoSedeLegale.via": "Officia voluptas vol",
      "indirizzoSedeLegale.civico": 35,
      "indirizzoSedeLegale.cap": 59,
      "indirizzoSedeLegale.localita": "Et deserunt possimus",
      "indirizzoSedeLegale.comune.id": 11,
      "indirizzoSedeLegale.comune.nome": "Dolorum voluptates a",
      "indirizzoSedeLegale.comune.provincia.id": 81,
      "indirizzoSedeLegale.comune.provincia.nome": "Maxime consectetur a",
      "indirizzoSedeLegale.comune.provincia.sigla": "Voluptatem Amet ut",
      "dataInserimento": 92,
      "dataUltimoContatto": 2,
      "id": 2
    },
    {
      "ragioneSociale": "Consequatur Ipsum a",
      "partitaIva": 74,
      "tipoCliente": "Ab mollitia deserunt",
      "email": "ducykabo@mailinator.com",
      "pec": "Dolor voluptas delec",
      "telefono": 79,
      "nomeContatto": "Ut possimus qui exe",
      "cognomeContatto": "Est impedit aut si",
      "telefonoContatto": 17,
      "emailContatto": "saxecuquh@mailinator.com",
      "indirizzoSedeOperativa.via": "Recusandae Officiis",
      "indirizzoSedeOperativa.civico": 25,
      "indirizzoSedeOperativa.cap": 9,
      "indirizzoSedeOperativa.localita": "Ipsum exercitatione",
      "indirizzoSedeOperativa.comune.id": 82,
      "indirizzoSedeOperativa.comune.nome": "Deserunt pariatur A",
      "indirizzoSedeOperativa.comune.provincia.id": 78,
      "indirizzoSedeOperativa.comune.provincia.nome": "Ad reprehenderit ip",
      "indirizzoSedeOperativa.comune.provincia.sigla": "Beatae adipisci magn",
      "indirizzoSedeLegale.via": "Aliquid et quisquam ",
      "indirizzoSedeLegale.civico": 57,
      "indirizzoSedeLegale.cap": 40,
      "indirizzoSedeLegale.localita": "Est voluptates aut n",
      "indirizzoSedeLegale.comune.id": 63,
      "indirizzoSedeLegale.comune.nome": "Sed et autem mollit ",
      "indirizzoSedeLegale.comune.provincia.id": 84,
      "indirizzoSedeLegale.comune.provincia.nome": "Adipisicing ut animi",
      "indirizzoSedeLegale.comune.provincia.sigla": "In a voluptatibus la",
      "dataInserimento": 37,
      "dataUltimoContatto": 57,
      "id": 3
    }
  ],
  "taxes": []
}